chanjing/__init__.py
chanjing/core.py
chanjing/schemas.py
chanjing/synthesis.py
chanjing/user_info.py
chanjing/customised/audio.py
chanjing/customised/person.py
chanjing-0.1.0.dist-info/METADATA
chanjing-0.1.0.dist-info/WHEEL
chanjing-0.1.0.dist-info/licenses/LICENSE
chanjing-0.1.0.dist-info/RECORD
