Metadata-Version: 2.4
Name: chanjing
Version: 0.1.0
Summary: 一个简单的数学工具库
Project-URL: Homepage, https://github.com/yourusername/dongjak-math-utils
Project-URL: Bug Tracker, https://github.com/yourusername/dongjak-math-utils/issues
Author-email: AiWorld Developer <dev@example.com>
License: MIT
License-File: LICENSE
Classifier: License :: OSI Approved :: MIT License
Classifier: Operating System :: OS Independent
Classifier: Programming Language :: Python :: 3
Requires-Python: >=3.12
Requires-Dist: pydantic>=2.10.6
Provides-Extra: dev
Requires-Dist: pytest>=6.0; extra == 'dev'
Requires-Dist: ruff>=0.0.254; extra == 'dev'
